repeated_test/__init__.py
repeated_test/_evaluated.py
repeated_test/core.py
repeated_test/utils.py
repeated_test/tests/__init__.py
repeated_test/tests/test_rt.py
repeated_test-2.3.3.dist-info/AUTHORS
repeated_test-2.3.3.dist-info/COPYING
repeated_test-2.3.3.dist-info/LICENSE.txt
repeated_test-2.3.3.dist-info/METADATA
repeated_test-2.3.3.dist-info/WHEEL
repeated_test-2.3.3.dist-info/top_level.txt
repeated_test-2.3.3.dist-info/RECORD
