Metadata-Version: 2.1
Name: repeated-test
Version: 2.3.3
Summary: A quick unittest-compatible framework for repeating a test function over many fixtures
Home-page: https://github.com/epsy/repeated_test
Author: Yann Kaiser
Author-email: kaiser.yann@gmail.com
License: MIT
Keywords: test,testing,unittest,fixtures
Classifier: Development Status :: 5 - Production/Stable
Classifier: Intended Audience :: Developers
Classifier: License :: OSI Approved :: MIT License
Classifier: Programming Language :: Python :: 3.5
Classifier: Programming Language :: Python :: 3.6
Classifier: Programming Language :: Python :: 3.7
Classifier: Programming Language :: Python :: 3.8
Classifier: Programming Language :: Python :: 3.9
Classifier: Programming Language :: Python :: 3.10
Classifier: Topic :: Software Development :: Quality Assurance
Classifier: Topic :: Software Development :: Testing
Requires-Python: >=3.5
License-File: LICENSE.txt
License-File: COPYING
License-File: AUTHORS
